taskwarrior_jrnl_hook/__init__.py
taskwarrior_jrnl_hook-0.1.5.dist-info/LICENSE.txt
taskwarrior_jrnl_hook-0.1.5.dist-info/METADATA
taskwarrior_jrnl_hook-0.1.5.dist-info/WHEEL
taskwarrior_jrnl_hook-0.1.5.dist-info/entry_points.txt
taskwarrior_jrnl_hook-0.1.5.dist-info/top_level.txt
taskwarrior_jrnl_hook-0.1.5.dist-info/RECORD
